delight/delight/DELIGHT_v1.h5
delight/delight/__init__.py
delight/delight/delight.py
astro_delight-0.0.11.dist-info/METADATA
astro_delight-0.0.11.dist-info/WHEEL
astro_delight-0.0.11.dist-info/top_level.txt
astro_delight-0.0.11.dist-info/RECORD
