Metadata-Version: 2.1
Name: astro-delight
Version: 0.0.11
Summary: Deep Learning Identification of Galaxy Hosts in Transients, a package to automatically identify host galaxies of transient candidates
Home-page: https://github.com/fforster/delight
Author: Francisco Förster
Author-email: francisco.forster@gmail.com
License: GNU GPLv3
Classifier: Development Status :: 4 - Beta
Classifier: Intended Audience :: Science/Research
Classifier: License :: OSI Approved :: GNU General Public License v3 (GPLv3)
Classifier: Operating System :: POSIX :: Linux
Classifier: Programming Language :: Python :: 3
Classifier: Programming Language :: Python :: 3.4
Classifier: Programming Language :: Python :: 3.5
Requires-Dist: astropy
Requires-Dist: astroquery
Requires-Dist: sep
Requires-Dist: xarray
Requires-Dist: matplotlib
Requires-Dist: numpy
Requires-Dist: tensorflow
